botbolt/__init__.py
botbolt/core.py
botbolt-0.1.0.dist-info/METADATA
botbolt-0.1.0.dist-info/WHEEL
botbolt-0.1.0.dist-info/licenses/LICENSE
botbolt-0.1.0.dist-info/RECORD
