Metadata-Version: 2.4
Name: botbolt
Version: 0.1.0
Summary: A beginner-friendly Python wrapper around nextcord for building Discord bots fast.
Author-email: Alex Ahern <alexahern417@gmail.com>
License: MIT License
License-File: LICENSE
Keywords: bot,discord,nextcord,wrapper
Classifier: Framework :: AsyncIO
Classifier: License :: OSI Approved :: MIT License
Classifier: Programming Language :: Python :: 3
Classifier: Topic :: Communications :: Chat
Classifier: Topic :: Internet :: WWW/HTTP
Requires-Python: >=3.9
Requires-Dist: nextcord>=2.6.0
